sphinx_autoindex/__init__.py
sphinx_autoindex/config.py
sphinx_autoindex/extension.py
sphinx_autoindex/generator.py
sphinx_autoindex/package.py
sphinx_autoindex-0.1.5.dist-info/METADATA
sphinx_autoindex-0.1.5.dist-info/WHEEL
sphinx_autoindex-0.1.5.dist-info/top_level.txt
sphinx_autoindex-0.1.5.dist-info/RECORD
