Metadata-Version: 2.4
Name: sphinx_autoindex
Version: 0.1.5
Summary: Sphinx extension to automatically index the source code for autodoc
Author: Mickael Descamps
Project-URL: Homepage, https://mickaeldescamps.github.io/sphinx-autoindex
Project-URL: Repository, https://github.com/MickaelDescamps/sphinx-autoindex
Project-URL: Issues, https://github.com/MickaelDescamps/sphinx-autoindex/issues
Classifier: Development Status :: 2 - Pre-Alpha
Classifier: Intended Audience :: Developers
Classifier: Framework :: Sphinx :: Extension
Classifier: Topic :: Documentation :: Sphinx
Classifier: Programming Language :: Python :: 3
Classifier: Programming Language :: Python :: 3.10
Classifier: Programming Language :: Python :: 3.11
Classifier: Programming Language :: Python :: 3.12
Classifier: Programming Language :: Python :: 3.13
Requires-Python: >=3.10
Requires-Dist: sphinx
Provides-Extra: docs
Requires-Dist: sphinx; extra == "docs"
Requires-Dist: sphinx-autodoc-typehints; extra == "docs"
Requires-Dist: sphinx-autoindex; extra == "docs"
Requires-Dist: sphinx-copybutton>=0.5.2; extra == "docs"
Requires-Dist: sphinx-prompt>=1.9.0; extra == "docs"
Requires-Dist: sphinx-rtd-theme>=3.0.2; extra == "docs"
Requires-Dist: sphinxemoji>=0.3.1; extra == "docs"
Requires-Dist: toml>=0.10.2; extra == "docs"
Requires-Dist: myst-parser>=4.0.1; extra == "docs"
